{
  "_fv": 6,
  "_type": "achievement",
  "definition": {
    "achievementName": "The Chalice Effect",
    "achievementDescription": "The Chalice Effect.",
    "achievementIcon": {
      "value": "CUSTOM:GoldenChalice"
    },
    "background": "Default",
    "disableDisplay": false,
    "showPopup": true,
    "announceToChat": true,
    "hideIfNotCompleted": true,
    "rewardLoot": [],
    "rewardRecipes": [],
    "rewardFunction": "No function",
    "rewardXP": 100,
    "achievementType": "challenge",
    "parent": {
      "value": "story/root"
    },
    "triggerxml": "<xml xmlns=\"https://developers.google.com/blockly/xml\"><block type=\"item_consumed\" x=\"37\" y=\"42\"><value name=\"item\"><block type=\"mcitem_all\"><field name=\"value\">CUSTOM:GoldenChalice</field></block></value><next><block type=\"advancement_trigger\" deletable=\"false\"/></next></block></xml>"
  }
}